nooneknowme
